medium_article_py/__init__.py
medium_article_py/medium.py
medium_article_py-0.1.10.dist-info/LICENSE
medium_article_py-0.1.10.dist-info/METADATA
medium_article_py-0.1.10.dist-info/WHEEL
medium_article_py-0.1.10.dist-info/top_level.txt
medium_article_py-0.1.10.dist-info/RECORD
