Metadata-Version: 2.1
Name: medium-article-py
Version: 0.1.10
Summary: A simple python library for Medium Articles APIs
Download-URL: https://github.com/muhammad-usman-108/medium-article-py.git
Author: Muhammad Usman
Author-email: umuhammad202@yahoo.com
Keywords: medium,medium-api,medium-article,api
Classifier: Programming Language :: Python :: 3
Classifier: License :: OSI Approved :: MIT License
Classifier: Operating System :: OS Independent
Requires-Python: >=3.6
License-File: LICENSE
Requires-Dist: requests
